LICENSE
README.md
setup.py
sibarras_fib_py/__init__.py
sibarras_fib_py/version.py
sibarras_fib_py.egg-info/PKG-INFO
sibarras_fib_py.egg-info/SOURCES.txt
sibarras_fib_py.egg-info/dependency_links.txt
sibarras_fib_py.egg-info/entry_points.txt
sibarras_fib_py.egg-info/requires.txt
sibarras_fib_py.egg-info/top_level.txt
sibarras_fib_py/cmd/__init__.py
sibarras_fib_py/cmd/fib_numb.py
sibarras_fib_py/fib_calcs/__init__.py
sibarras_fib_py/fib_calcs/fib_number.py
sibarras_fib_py/fib_calcs/fib_numbers.py
tests/sibarras_fib_py/__init__.py
tests/sibarras_fib_py/fib_calcs/__init__.py
tests/sibarras_fib_py/fib_calcs/test_fib_number.py
tests/sibarras_fib_py/fib_calcs/test_fib_numbers.py