Metadata-Version: 2.1
Name: sibarras-fib-py
Version: 0.0.2
Summary: Calculates a fibonacci number
Home-page: https://github.com/sibarras/sibarras-fib-py.git
Author: Samuel Ibarra
Author-email: ing.samuelibarra@gmail.com
License: UNKNOWN
Platform: UNKNOWN
Classifier: Development Status :: 4 - Beta
Classifier: Programming Language :: Python :: 3
Classifier: Operating System :: OS Independent
Requires-Python: >=3.10
Provides-Extra: server
License-File: LICENSE
